Metadata-Version: 1.1
Name: robotframework-imagetotextlibrary
Version: 0.0.1
Summary: Robot Framework library for coverting image to text
Home-page: https://github.com/alvingalangcitaka/robotframework-imagetotextlibrary
Author: Alvin Galang Citaka
Author-email: alvingalangcitaka@gmail.com
License: MIT
Keywords: tesseractlibrary
Platform: UNKNOWN
Classifier: Development Status :: 2 - Pre-Alpha
Classifier: Programming Language :: Python :: 2
Classifier: Programming Language :: Python :: 3
Classifier: Operating System :: OS Independent
Classifier: Topic :: Software Development :: Testing
Classifier: License :: OSI Approved :: MIT License
